fpyga/__init__.py
fpyga/_nbdev.py
fpyga/devices.py
fpyga/projects.py
fpyga/scripting.py
fpyga-0.0.2.dist-info/LICENSE
fpyga-0.0.2.dist-info/METADATA
fpyga-0.0.2.dist-info/WHEEL
fpyga-0.0.2.dist-info/entry_points.txt
fpyga-0.0.2.dist-info/top_level.txt
fpyga-0.0.2.dist-info/RECORD
