Metadata-Version: 2.1
Name: fpyga
Version: 0.0.2
Summary: FPGA Python interface.
Home-page: https://github.com/Noeloikeau/fpyga/tree/master/
Author: Noeloikeau
Author-email: noeloikeau@gmail.com
License: Apache Software License 2.0
Keywords: FPGA,Python,Quartus,Intel
Platform: UNKNOWN
Classifier: Development Status :: 3 - Alpha
Classifier: Intended Audience :: Developers
Classifier: Natural Language :: English
Classifier: Programming Language :: Python :: 3.6
Classifier: Programming Language :: Python :: 3.7
Classifier: Programming Language :: Python :: 3.8
Classifier: License :: OSI Approved :: Apache Software License
Requires-Python: >=3.6
Requires-Dist: pip
Requires-Dist: packaging
Provides-Extra: dev
